deriva/__init__.py
deriva/config/__init__.py
deriva/config/acl_config.py
deriva/config/annotation_config.py
deriva/config/annotation_validate.py
deriva/config/base_config.py
deriva/config/dump_catalog_annotations.py
deriva/config/rollback_annotation.py
deriva/config/examples/group_owner_policy.json
deriva/config/examples/self_serve_policy.json
deriva/core/__init__.py
deriva/core/annotation.py
deriva/core/base_cli.py
deriva/core/catalog_cli.py
deriva/core/datapath.py
deriva/core/deriva_binding.py
deriva/core/deriva_server.py
deriva/core/ermrest_catalog.py
deriva/core/ermrest_model.py
deriva/core/hatrac_cli.py
deriva/core/hatrac_store.py
deriva/core/mmo.py
deriva/core/polling_ermrest_catalog.py
deriva/core/schemas/app_links.schema.json
deriva/core/schemas/asset.schema.json
deriva/core/schemas/bulk_upload.schema.json
deriva/core/schemas/chaise_config.schema.json
deriva/core/schemas/citation.schema.json
deriva/core/schemas/column_display.schema.json
deriva/core/schemas/display.schema.json
deriva/core/schemas/export.schema.json
deriva/core/schemas/export_2019.schema.json
deriva/core/schemas/foreign_key.schema.json
deriva/core/schemas/generated.schema.json
deriva/core/schemas/immutable.schema.json
deriva/core/schemas/indexing_preferences.schema.json
deriva/core/schemas/key_display.schema.json
deriva/core/schemas/non_deletable.schema.json
deriva/core/schemas/required.schema.json
deriva/core/schemas/source_definitions.schema.json
deriva/core/schemas/table_alternatives.schema.json
deriva/core/schemas/table_display.schema.json
deriva/core/schemas/visible_columns.schema.json
deriva/core/schemas/visible_foreign_keys.schema.json
deriva/core/tests/__init__.py
deriva/core/utils/__init__.py
deriva/core/utils/core_utils.py
deriva/core/utils/credenza_auth_utils.py
deriva/core/utils/globus_auth_utils.py
deriva/core/utils/hash_utils.py
deriva/core/utils/mime_utils.py
deriva/core/utils/version_utils.py
deriva/core/utils/webauthn_utils.py
deriva/seo/__init__.py
deriva-1.7.11.dist-info/licenses/LICENSE
deriva-1.7.11.dist-info/METADATA
deriva-1.7.11.dist-info/WHEEL
deriva-1.7.11.dist-info/entry_points.txt
deriva-1.7.11.dist-info/top_level.txt
deriva-1.7.11.dist-info/RECORD
