Metadata-Version: 2.4
Name: deriva
Version: 1.7.11
Summary: Python APIs and CLIs (Command-Line Interfaces) for the DERIVA platform.
Home-page: https://github.com/informatics-isi-edu/deriva-py
Author: USC Information Sciences Institute, Informatics Systems Research Division
Author-email: isrd-support@isi.edu
Maintainer: USC Information Sciences Institute, Informatics Systems Research Division
Maintainer-email: isrd-support@isi.edu
License: Apache 2.0
Classifier: Intended Audience :: Science/Research
Classifier: Intended Audience :: Developers
Classifier: License :: OSI Approved :: Apache Software License
Classifier: Operating System :: POSIX
Classifier: Operating System :: MacOS :: MacOS X
Classifier: Operating System :: Microsoft :: Windows
Classifier: Programming Language :: Python
Classifier: Programming Language :: Python :: 3.9
Classifier: Programming Language :: Python :: 3.10
Classifier: Programming Language :: Python :: 3.11
Classifier: Programming Language :: Python :: 3.12
Requires-Python: >=3.8, <4
License-File: LICENSE
Requires-Dist: packaging
Requires-Dist: requests
Requires-Dist: pika
Requires-Dist: urllib3<3,>=1.26.20
Requires-Dist: portalocker>=1.2.1
Requires-Dist: bdbag>=1.8.0
Requires-Dist: globus_sdk<4,>=3
Requires-Dist: fair-research-login>=0.3.1
Requires-Dist: fair-identifiers-client>=0.5.1
Requires-Dist: jsonschema>=3.1
Dynamic: author
Dynamic: author-email
Dynamic: classifier
Dynamic: description
Dynamic: description-content-type
Dynamic: home-page
Dynamic: license
Dynamic: license-file
Dynamic: maintainer
Dynamic: maintainer-email
Dynamic: requires-dist
Dynamic: requires-python
Dynamic: summary
